<annotation verified="no">
  <folder>JPEGImages</folder>
  <filename>13</filename>
  <path>/Users/huhao/Documents/cv_project/stick_barcode/Semantic_Segmentation/dateset/label_dateset/JPEGImages/13.png</path>
  <source>
    <database>Unknown</database>
  </source>
  <size>
    <width>528</width>
    <height>752</height>
    <depth>3</depth>
  </size>
  <segmented>0</segmented>
  <object>
    <type>bndbox</type>
    <name>Text_area</name>
    <pose>Unspecified</pose>
    <truncated>0</truncated>
    <difficult>0</difficult>
    <bndbox>
      <xmin>91</xmin>
      <ymin>457</ymin>
      <xmax>455</xmax>
      <ymax>582</ymax>
    </bndbox>
  </object>
  <object>
    <type>bndbox</type>
    <name>Text_area</name>
    <pose>Unspecified</pose>
    <truncated>0</truncated>
    <difficult>0</difficult>
    <bndbox>
      <xmin>333</xmin>
      <ymin>648</ymin>
      <xmax>495</xmax>
      <ymax>704</ymax>
    </bndbox>
  </object>
  <object>
    <type>bndbox</type>
    <name>Text_area</name>
    <pose>Unspecified</pose>
    <truncated>0</truncated>
    <difficult>0</difficult>
    <bndbox>
      <xmin>174</xmin>
      <ymin>40</ymin>
      <xmax>348</xmax>
      <ymax>184</ymax>
    </bndbox>
  </object>
  <object>
    <type>robndbox</type>
    <name>Text_area</name>
    <pose>Unspecified</pose>
    <truncated>0</truncated>
    <difficult>0</difficult>
    <robndbox>
      <cx>109.2895</cx>
      <cy>689.4737</cy>
      <w>177.0</w>
      <h>110.0</h>
      <angle>0.0</angle>
    </robndbox>
  </object>
</annotation>
