<annotation verified="no">
  <folder>JPEGImages</folder>
  <filename>15</filename>
  <path>/Users/huhao/Documents/cv_project/stick_barcode/Semantic_Segmentation/dateset/label_dateset/JPEGImages/15.png</path>
  <source>
    <database>Unknown</database>
  </source>
  <size>
    <width>490</width>
    <height>742</height>
    <depth>3</depth>
  </size>
  <segmented>0</segmented>
  <object>
    <type>bndbox</type>
    <name>Text_area</name>
    <pose>Unspecified</pose>
    <truncated>0</truncated>
    <difficult>0</difficult>
    <bndbox>
      <xmin>113</xmin>
      <ymin>20</ymin>
      <xmax>340</xmax>
      <ymax>154</ymax>
    </bndbox>
  </object>
  <object>
    <type>bndbox</type>
    <name>Text_area</name>
    <pose>Unspecified</pose>
    <truncated>0</truncated>
    <difficult>0</difficult>
    <bndbox>
      <xmin>112</xmin>
      <ymin>197</ymin>
      <xmax>340</xmax>
      <ymax>361</ymax>
    </bndbox>
  </object>
  <object>
    <type>bndbox</type>
    <name>Text_area</name>
    <pose>Unspecified</pose>
    <truncated>0</truncated>
    <difficult>0</difficult>
    <bndbox>
      <xmin>394</xmin>
      <ymin>12</ymin>
      <xmax>477</xmax>
      <ymax>98</ymax>
    </bndbox>
  </object>
  <object>
    <type>bndbox</type>
    <name>Text_area</name>
    <pose>Unspecified</pose>
    <truncated>0</truncated>
    <difficult>0</difficult>
    <bndbox>
      <xmin>133</xmin>
      <ymin>559</ymin>
      <xmax>343</xmax>
      <ymax>691</ymax>
    </bndbox>
  </object>
</annotation>
